{
  "backgroundTexture": "skilltree:textures/icons/background/lesser.png",
  "bonuses": [
    {
      "type": "skilltree:attribute",
      "amount": 1.0,
      "attribute": "skilltree:evasion",
      "id": "910b70c2-b222-4c8c-93f6-4b54eace91dd",
      "name": "SkillBonus",
      "operation": 0,
      "player_condition": {
        "type": "skilltree:none"
      },
      "player_multiplier": {
        "type": "skilltree:none"
      }
    }
  ],
  "borderTexture": "skilltree:textures/tooltip/lesser.png",
  "buttonSize": 16,
  "connectedAsGateways": [],
  "connectedSkills": [
    "skilltree:alchemist_defensive_8",
    "skilltree:alchemist_lesser_1"
  ],
  "iconTexture": "skilltree:textures/icons/alchemist_defensive_1.png",
  "id": "skilltree:alchemist_defensive_7",
  "isStartingPoint": false,
  "positionX": 53.99701,
  "positionY": 323.53247
}