{
  "backgroundTexture": "skilltree:textures/icons/background/lesser.png",
  "bonuses": [
    {
      "type": "skilltree:attribute",
      "amount": 0.5,
      "attribute": "skilltree:evasion",
      "id": "603ffa00-3197-4bc1-8594-43526ece1793",
      "name": "SkillBonus",
      "operation": 0,
      "player_condition": {
        "type": "skilltree:none"
      },
      "player_multiplier": {
        "type": "skilltree:none"
      }
    },
    {
      "type": "skilltree:attribute",
      "amount": 0.5,
      "attribute": "minecraft:generic.armor",
      "id": "741a82ac-41a7-47f4-a001-bdf1a65c2bb3",
      "name": "SkillBonus",
      "operation": 0,
      "player_condition": {
        "type": "skilltree:none"
      },
      "player_multiplier": {
        "type": "skilltree:none"
      }
    }
  ],
  "borderTexture": "skilltree:textures/tooltip/lesser.png",
  "buttonSize": 16,
  "connectedAsGateways": [],
  "connectedSkills": [
    "skilltree:alchemist_subclass_1_defensive_3"
  ],
  "iconTexture": "skilltree:textures/icons/alchemist_subclass_1_defensive_1.png",
  "id": "skilltree:alchemist_subclass_1_defensive_2",
  "isStartingPoint": false,
  "positionX": -118.95877,
  "positionY": 238.04474
}