{
  "backgroundTexture": "skilltree:textures/icons/background/class.png",
  "bonuses": [
    {
      "type": "skilltree:attribute",
      "amount": 0.05,
      "attribute": "skilltree:crit_chance",
      "id": "8f69a439-101e-44f3-b864-575d221ced01",
      "name": "SkillBonus",
      "operation": 1
    },
    {
      "type": "skilltree:attribute",
      "amount": 0.15,
      "attribute": "skilltree:crit_damage",
      "id": "9f8fdb0e-99f9-4acd-b3f6-2963c4342aeb",
      "name": "SkillBonus",
      "operation": 1
    }
  ],
  "borderTexture": "skilltree:textures/tooltip/keystone.png",
  "buttonSize": 24,
  "connectedAsGateways": [],
  "connectedSkills": [
    "skilltree:alchemist_subclass_1_offensive_1",
    "skilltree:alchemist_subclass_1_crafting_1"
  ],
  "iconTexture": "skilltree:textures/icons/alchemist_subclass_1.png",
  "id": "skilltree:alchemist_subclass_1",
  "isStartingPoint": false,
  "positionX": -144.95734,
  "positionY": 315.07642
}