{
  "attributeModifiers": [
    {
      "attribute": "skilltree:damage_against_poisoned",
      "modifier": {
        "amount": 0.05,
        "id": "a5869b3b-1665-47b6-b46b-b56e10ed3db8",
        "nameGetter": "PassiveSkill",
        "operation": "MULTIPLY_BASE"
      }
    }
  ],
  "backgroundTexture": "skilltree:textures/icons/background/lesser.png",
  "borderTexture": "skilltree:textures/tooltip/lesser.png",
  "buttonSize": 16,
  "commands": [],
  "connectedSkills": [
    "skilltree:alchemist_life_2",
    "skilltree:alchemist_offensive_5"
  ],
  "iconTexture": "skilltree:textures/icons/alchemist_offensive_1.png",
  "id": "skilltree:alchemist_offensive_4",
  "isStartingPoint": false,
  "positionX": -61.997005,
  "positionY": 237.52727
}