{
  "backgroundTexture": "skilltree:textures/icons/background/lesser.png",
  "bonuses": [
    {
      "type": "skilltree:attribute",
      "amount": 0.05,
      "attribute": "skilltree:damage_with_shield",
      "id": "0ef370fb-8937-4c12-a3d0-a153aeab04a0",
      "name": "SkillBonus",
      "operation": 1
    }
  ],
  "borderTexture": "skilltree:textures/tooltip/lesser.png",
  "buttonSize": 16,
  "connectedAsGateways": [],
  "connectedSkills": [
    "skilltree:blacksmith_offensive_3"
  ],
  "iconTexture": "skilltree:textures/icons/blacksmith_offensive_1.png",
  "id": "skilltree:blacksmith_offensive_2",
  "isStartingPoint": false,
  "positionX": -159.62946,
  "positionY": -124.50673
}