{
  "attributeModifiers": [
    {
      "attribute": "minecraft:generic.armor",
      "modifier": {
        "amount": 1.0,
        "id": "0b4c40d3-eea6-47d4-b06e-9b24b9a01163",
        "nameGetter": "PassiveSkill",
        "operation": "ADDITION"
      }
    }
  ],
  "backgroundTexture": "skilltree:textures/icons/background/lesser.png",
  "borderTexture": "skilltree:textures/tooltip/lesser.png",
  "buttonSize": 16,
  "commands": [],
  "connectedAsGateways": [],
  "connectedSkills": [
    "skilltree:blacksmith_defensive_3"
  ],
  "iconTexture": "skilltree:textures/icons/blacksmith_defensive_1.png",
  "id": "skilltree:blacksmith_defensive_2",
  "isStartingPoint": false,
  "positionX": -187.631,
  "positionY": -76.008415
}