{
  "attributeModifiers": [
    {
      "attribute": "skilltree:life_regeneration_bonus",
      "modifier": {
        "amount": 0.25,
        "id": "647abf62-1c30-4a63-b92c-7213efbbd0b1",
        "nameGetter": "PassiveSkill",
        "operation": "ADDITION"
      }
    }
  ],
  "backgroundTexture": "skilltree:textures/icons/background/lesser.png",
  "borderTexture": "skilltree:textures/tooltip/lesser.png",
  "buttonSize": 16,
  "commands": [],
  "connectedSkills": [
    "skilltree:blacksmith_healing_notable_1"
  ],
  "iconTexture": "skilltree:textures/icons/blacksmith_healing_1.png",
  "id": "skilltree:blacksmith_healing_4",
  "isStartingPoint": false,
  "positionX": -147.24622,
  "positionY": -7.62364
}