{
  "backgroundTexture": "skilltree:textures/icons/background/lesser.png",
  "bonuses": [
    {
      "type": "skilltree:crafted_item_bonus",
      "item_bonus": {
        "type": "skilltree:skill_bonus",
        "skill_bonus": {
          "type": "skilltree:attribute",
          "amount": 2.0,
          "attribute": "minecraft:generic.armor",
          "id": "8763c2ca-19d2-4008-a49d-a258f6e6146c",
          "name": "SkillBonus",
          "operation": 0,
          "player_condition": {
            "type": "skilltree:none"
          },
          "player_multiplier": {
            "type": "skilltree:none"
          }
        }
      },
      "item_condition": {
        "type": "skilltree:armor",
        "armor_type": "shield"
      }
    }
  ],
  "borderTexture": "skilltree:textures/tooltip/lesser.png",
  "buttonSize": 16,
  "connectedAsGateways": [],
  "connectedSkills": [
    "skilltree:blacksmith_crafting_3"
  ],
  "iconTexture": "skilltree:textures/icons/blacksmith_crafting_1.png",
  "id": "skilltree:blacksmith_crafting_2",
  "isStartingPoint": false,
  "positionX": -81.40338,
  "positionY": -47.005203
}