{
  "backgroundTexture": "skilltree:textures/icons/background/lesser.png",
  "bonuses": [
    {
      "type": "skilltree:attribute",
      "amount": 0.5,
      "attribute": "minecraft:generic.armor",
      "id": "5b915d57-d795-4d26-acf5-862781812d00",
      "name": "SkillBonus",
      "operation": 0,
      "player_condition": {
        "type": "skilltree:none"
      },
      "player_multiplier": {
        "type": "skilltree:none"
      }
    },
    {
      "type": "skilltree:attribute",
      "amount": 0.5,
      "attribute": "skilltree:blocking",
      "id": "ca50672c-11e4-4128-b538-5f7908383c84",
      "name": "SkillBonus",
      "operation": 0,
      "player_condition": {
        "type": "skilltree:none"
      },
      "player_multiplier": {
        "type": "skilltree:none"
      }
    }
  ],
  "borderTexture": "skilltree:textures/tooltip/lesser.png",
  "buttonSize": 16,
  "directConnections": [
    "skilltree:cook_subclass_2_defensive_3"
  ],
  "iconTexture": "skilltree:textures/icons/cook_subclass_2_defensive_1.png",
  "id": "skilltree:cook_subclass_2_defensive_2",
  "isStartingPoint": false,
  "longConnections": [],
  "oneWayConnections": [],
  "positionX": -118.95877,
  "positionY": -238.0512
}