{
  "backgroundTexture": "skilltree:textures/icons/background/lesser.png",
  "bonuses": [
    {
      "type": "skilltree:attribute",
      "amount": 0.5,
      "attribute": "minecraft:generic.armor",
      "id": "1aaf7eac-c737-4e0a-98bd-11e8d744c8a1",
      "name": "SkillBonus",
      "operation": 0,
      "player_condition": {
        "type": "skilltree:none"
      },
      "player_multiplier": {
        "type": "skilltree:none"
      }
    },
    {
      "type": "skilltree:attribute",
      "amount": 0.5,
      "attribute": "skilltree:blocking",
      "id": "847d7bb4-d36e-4644-a151-39f2fee1020b",
      "name": "SkillBonus",
      "operation": 0,
      "player_condition": {
        "type": "skilltree:none"
      },
      "player_multiplier": {
        "type": "skilltree:none"
      }
    }
  ],
  "borderTexture": "skilltree:textures/tooltip/lesser.png",
  "buttonSize": 16,
  "connectedAsGateways": [],
  "connectedSkills": [
    "skilltree:cook_subclass_2_defensive_4"
  ],
  "iconTexture": "skilltree:textures/icons/cook_subclass_2_defensive_1.png",
  "id": "skilltree:cook_subclass_2_defensive_3",
  "isStartingPoint": false,
  "positionX": -131.95805,
  "positionY": -260.56827
}