{
  "attributeModifiers": [
    {
      "attribute": "minecraft:generic.attack_speed",
      "modifier": {
        "amount": 0.01,
        "id": "c2eab88e-e6d7-4f0a-bbc3-aca4b73ba544",
        "nameGetter": "PassiveSkill",
        "operation": "MULTIPLY_BASE"
      }
    }
  ],
  "backgroundTexture": "skilltree:textures/icons/background/lesser.png",
  "borderTexture": "skilltree:textures/tooltip/lesser.png",
  "buttonSize": 16,
  "commands": [],
  "connectedAsGateways": [],
  "connectedSkills": [
    "skilltree:cook_subclass_1_offensive_3"
  ],
  "iconTexture": "skilltree:textures/icons/cook_subclass_1_offensive_1.png",
  "id": "skilltree:cook_subclass_1_offensive_2",
  "isStartingPoint": false,
  "positionX": 128.9708,
  "positionY": -368.78476
}