{
  "attributeModifiers": [
    {
      "attribute": "skilltree:block_chance",
      "modifier": {
        "amount": 0.01,
        "id": "1d409fae-69dc-49ba-9b94-0945cffc1a20",
        "nameGetter": "PassiveSkill",
        "operation": "MULTIPLY_BASE"
      }
    }
  ],
  "backgroundTexture": "skilltree:textures/icons/background/lesser.png",
  "borderTexture": "skilltree:textures/tooltip/lesser.png",
  "buttonSize": 16,
  "commands": [],
  "connectedAsGateways": [],
  "connectedSkills": [
    "skilltree:enchanter_defensive_8",
    "skilltree:enchanter_lesser_1"
  ],
  "iconTexture": "skilltree:textures/icons/enchanter_defensive_1.png",
  "id": "skilltree:enchanter_defensive_7",
  "isStartingPoint": false,
  "positionX": 253.19548,
  "positionY": -208.52092
}