{
  "attributeModifiers": [
    {
      "attribute": "skilltree:chance_to_apply_better_enchantment",
      "modifier": {
        "amount": 1.0,
        "id": "00f6d3c6-71f5-447a-9a31-3615355dd5ff",
        "nameGetter": "PassiveSkill",
        "operation": "MULTIPLY_BASE"
      }
    }
  ],
  "backgroundTexture": "skilltree:textures/icons/background/keystone.png",
  "borderTexture": "skilltree:textures/tooltip/keystone.png",
  "buttonSize": 24,
  "commands": [],
  "connectedSkills": [],
  "iconTexture": "skilltree:textures/icons/enchanter_mastery.png",
  "id": "skilltree:enchanter_mastery",
  "isStartingPoint": false,
  "positionX": 351.2064,
  "positionY": -202.75761
}