{
  "attributeModifiers": [
    {
      "attribute": "skilltree:block_chance",
      "modifier": {
        "amount": 0.01,
        "id": "29a5ddce-8ba5-484c-b6b1-682b4d22ba46",
        "nameGetter": "PassiveSkill",
        "operation": "MULTIPLY_BASE"
      }
    }
  ],
  "backgroundTexture": "skilltree:textures/icons/background/lesser.png",
  "borderTexture": "skilltree:textures/tooltip/lesser.png",
  "buttonSize": 16,
  "commands": [],
  "connectedAsGateways": [],
  "connectedSkills": [
    "skilltree:enchanter_life_1",
    "skilltree:enchanter_defensive_5"
  ],
  "iconTexture": "skilltree:textures/icons/enchanter_defensive_1.png",
  "id": "skilltree:enchanter_defensive_4",
  "isStartingPoint": false,
  "positionX": 185.64426,
  "positionY": -169.52307
}