{
  "attributeModifiers": [
    {
      "attribute": "skilltree:block_chance",
      "modifier": {
        "amount": 0.01,
        "id": "5bb2b5c5-5c8b-4c61-9ff2-37f9eee85665",
        "nameGetter": "PassiveSkill",
        "operation": "MULTIPLY_BASE"
      }
    }
  ],
  "backgroundTexture": "skilltree:textures/icons/background/lesser.png",
  "borderTexture": "skilltree:textures/tooltip/lesser.png",
  "buttonSize": 16,
  "commands": [],
  "connectedSkills": [
    "skilltree:enchanter_defensive_4"
  ],
  "iconTexture": "skilltree:textures/icons/enchanter_defensive_1.png",
  "id": "skilltree:enchanter_defensive_3",
  "isStartingPoint": false,
  "positionX": 164.64282,
  "positionY": -155.00725
}