{
  "attribute_bonus": {
    "attribute": "skilltree:player.crit_chance_bonus_per_enchanted_item",
    "bonus": 0.01,
    "operation": "addition",
    "unique_id": "53a88af5-8822-45fe-80ed-65254a2b153f"
  },
  "background_texture": "skilltree:textures/icons/background/lesser.png",
  "button_size": 16,
  "connections": [
    "skilltree:enchanter_lesser_right_7"
  ],
  "icon_texture": "skilltree:textures/icons/enchanter_lesser_right_upper.png",
  "position": {
    "x": 56,
    "y": -155
  },
  "tree": "skilltree:tree"
}