{
  "attribute_modifiers": [
    {
      "amount": 2.0,
      "attribute": "skilltree:player.maximum_life_with_enchanted_item",
      "operation": "addition",
      "unique_id": "ef4424b1-49bb-42cc-8814-b0d4352bb7b0"
    }
  ],
  "background_texture": "skilltree:textures/icons/background/lesser.png",
  "button_size": 16,
  "connections": [
    "skilltree:enchanter_defensive_combat_8",
    "skilltree:enchanter_mixed_notable_1",
    "skilltree:enchanter_defensive_combat_10"
  ],
  "icon_texture": "skilltree:textures/icons/enchanter_defensive_combat_2.png",
  "position": {
    "x": 179,
    "y": -85
  },
  "tree": "skilltree:tree"
}