{
  "backgroundTexture": "skilltree:textures/icons/background/notable.png",
  "bonuses": [
    {
      "type": "skilltree:attribute",
      "amount": 0.25,
      "attribute": "skilltree:life_on_block",
      "id": "98d51b08-ccfc-471e-9dbb-c387bf5aa01f",
      "name": "SkillBonus",
      "operation": 0,
      "player_condition": {
        "type": "skilltree:none"
      },
      "player_multiplier": {
        "type": "skilltree:enchants_amount",
        "item_condition": {
          "type": "skilltree:equipment_type",
          "equipment_type": "shield"
        }
      }
    }
  ],
  "borderTexture": "skilltree:textures/tooltip/notable.png",
  "buttonSize": 20,
  "directConnections": [],
  "iconTexture": "skilltree:textures/icons/enchanter_healing_notable_1.png",
  "id": "skilltree:enchanter_healing_notable_1",
  "isStartingPoint": false,
  "longConnections": [],
  "oneWayConnections": [],
  "positionX": 54.295937,
  "positionY": -94.80734
}