{
  "backgroundTexture": "skilltree:textures/icons/background/lesser.png",
  "bonuses": [
    {
      "type": "skilltree:attribute",
      "amount": 1.0,
      "attribute": "skilltree:evasion",
      "id": "44e2ac6e-51f8-4b6d-b30f-b04d5b95538d",
      "name": "SkillBonus",
      "operation": 0,
      "player_condition": {
        "type": "skilltree:none"
      },
      "player_multiplier": {
        "type": "skilltree:none"
      }
    }
  ],
  "borderTexture": "skilltree:textures/tooltip/lesser.png",
  "buttonSize": 16,
  "connectedAsGateways": [],
  "connectedSkills": [
    "skilltree:hunter_defensive_keystone_1"
  ],
  "iconTexture": "skilltree:textures/icons/hunter_defensive_1.png",
  "id": "skilltree:hunter_defensive_8",
  "isStartingPoint": false,
  "positionX": 329.69434,
  "positionY": 128.01418
}