{
  "backgroundTexture": "skilltree:textures/icons/background/lesser.png",
  "bonuses": [
    {
      "type": "skilltree:attribute",
      "amount": 0.5,
      "attribute": "skilltree:evasion",
      "id": "7a63fcb0-1acf-4b82-91ac-5797b91a5f84",
      "name": "SkillBonus",
      "operation": 0
    },
    {
      "type": "skilltree:attribute",
      "amount": 0.5,
      "attribute": "skilltree:blocking",
      "id": "029c58d7-9e5f-482a-a4f2-42037eb40216",
      "name": "SkillBonus",
      "operation": 0
    }
  ],
  "borderTexture": "skilltree:textures/tooltip/lesser.png",
  "buttonSize": 16,
  "connectedAsGateways": [],
  "connectedSkills": [
    "skilltree:hunter_subclass_2"
  ],
  "iconTexture": "skilltree:textures/icons/hunter_subclass_2_defensive_1.png",
  "id": "skilltree:hunter_subclass_2_defensive_4",
  "isStartingPoint": false,
  "positionX": 317.63098,
  "positionY": 16.008415
}