{
  "attributeModifiers": [
    {
      "attribute": "skilltree:crafted_quivers_capacity",
      "modifier": {
        "amount": 0.05,
        "id": "9540e211-4abc-4ecc-85c6-972334802150",
        "nameGetter": "PassiveSkill",
        "operation": "MULTIPLY_BASE"
      }
    }
  ],
  "backgroundTexture": "skilltree:textures/icons/background/lesser.png",
  "borderTexture": "skilltree:textures/tooltip/lesser.png",
  "buttonSize": 16,
  "commands": [],
  "connectedAsGateways": [],
  "connectedSkills": [
    "skilltree:enchanter_subclass_special"
  ],
  "iconTexture": "skilltree:textures/icons/hunter_subclass_2_crafting_1.png",
  "id": "skilltree:hunter_subclass_2_crafting_5",
  "isStartingPoint": false,
  "positionX": 422.37567,
  "positionY": 32.01235
}