{
  "backgroundTexture": "skilltree:textures/icons/background/lesser.png",
  "bonuses": [
    {
      "type": "skilltree:attribute",
      "amount": 0.05,
      "attribute": "skilltree:double_loot_chance",
      "id": "0bee8dbb-6eb8-4768-bb4f-aa8ec88ff0a6",
      "name": "SkillBonus",
      "operation": 1
    }
  ],
  "borderTexture": "skilltree:textures/tooltip/lesser.png",
  "buttonSize": 16,
  "connectedAsGateways": [],
  "connectedSkills": [],
  "iconTexture": "skilltree:textures/icons/hunter_lesser_1.png",
  "id": "skilltree:hunter_lesser_3",
  "isStartingPoint": false,
  "positionX": 316.69507,
  "positionY": 150.53
}