{
  "attributeModifiers": [
    {
      "attribute": "skilltree:gem_power_in_armor",
      "modifier": {
        "amount": 0.1,
        "id": "f5df5835-51ab-42b0-a114-007aa48f9334",
        "nameGetter": "PassiveSkill",
        "operation": "MULTIPLY_BASE"
      }
    }
  ],
  "backgroundTexture": "skilltree:textures/icons/background/lesser.png",
  "borderTexture": "skilltree:textures/tooltip/lesser.png",
  "buttonSize": 16,
  "commands": [],
  "connectedSkills": [
    "skilltree:miner_defensive_crafting_3"
  ],
  "iconTexture": "skilltree:textures/icons/miner_defensive_crafting_1.png",
  "id": "skilltree:miner_defensive_crafting_2",
  "isStartingPoint": false,
  "positionX": -126.65993,
  "positionY": 105.51328
}