{
  "backgroundTexture": "skilltree:textures/icons/background/lesser.png",
  "bonuses": [
    {
      "type": "skilltree:attribute",
      "amount": 0.5,
      "attribute": "skilltree:evasion",
      "id": "fd59a775-3c9a-4ad5-bc7b-65755da94faf",
      "name": "SkillBonus",
      "operation": 0,
      "player_condition": {
        "type": "skilltree:none"
      },
      "player_multiplier": {
        "type": "skilltree:none"
      }
    },
    {
      "type": "skilltree:attribute",
      "amount": 0.5,
      "attribute": "minecraft:generic.armor",
      "id": "cced1318-aca4-4f6f-8a9a-c6dc75403017",
      "name": "SkillBonus",
      "operation": 0,
      "player_condition": {
        "type": "skilltree:none"
      },
      "player_multiplier": {
        "type": "skilltree:none"
      }
    }
  ],
  "borderTexture": "skilltree:textures/tooltip/lesser.png",
  "buttonSize": 16,
  "directConnections": [
    "skilltree:miner_subclass_2"
  ],
  "iconTexture": "skilltree:textures/icons/miner_subclass_2_defensive_1.png",
  "id": "skilltree:miner_subclass_2_defensive_4",
  "isStartingPoint": false,
  "longConnections": [],
  "oneWayConnections": [],
  "positionX": -172.68896,
  "positionY": 267.07388
}