{
  "attributeModifiers": [
    {
      "attribute": "curios:ring",
      "modifier": {
        "amount": 1.0,
        "id": "1e98cb25-b368-46e4-bdcb-84db301e4461",
        "nameGetter": "PassiveSkill",
        "operation": "ADDITION"
      }
    }
  ],
  "backgroundTexture": "skilltree:textures/icons/background/keystone.png",
  "borderTexture": "skilltree:textures/tooltip/keystone.png",
  "buttonSize": 24,
  "commands": [],
  "connectedSkills": [
    "skilltree:miner_subclass_2_life_4"
  ],
  "iconTexture": "skilltree:textures/icons/miner_subclass_2_mastery.png",
  "id": "skilltree:miner_subclass_2_mastery",
  "isStartingPoint": false,
  "positionX": -315.95526,
  "positionY": 349.7826
}