{
  "attributeModifiers": [
    {
      "attribute": "minecraft:generic.armor",
      "modifier": {
        "amount": 1.0,
        "id": "f83f8f9c-a6bd-4f71-9839-a47f69ba35c3",
        "nameGetter": "PassiveSkill",
        "operation": "ADDITION"
      }
    }
  ],
  "backgroundTexture": "skilltree:textures/icons/background/lesser.png",
  "borderTexture": "skilltree:textures/tooltip/lesser.png",
  "buttonSize": 16,
  "commands": [],
  "connectedSkills": [
    "skilltree:miner_life_1",
    "skilltree:miner_defensive_5"
  ],
  "iconTexture": "skilltree:textures/icons/miner_defensive_1.png",
  "id": "skilltree:miner_defensive_4",
  "isStartingPoint": false,
  "positionX": -185.64426,
  "positionY": 169.52307
}