{
  "bonuses": [
    {
      "bonus_provider": {
        "type": "skilltree:random",
        "bonuses": [
          {
            "bonus_provider": {
              "type": "skilltree:simple",
              "item_bonus": {
                "type": "skilltree:skill_bonus",
                "skill_bonus": {
                  "type": "skilltree:attribute",
                  "amount": 0.09999999776482582,
                  "attribute": "skilltree:evasion",
                  "id": "416b1234-6a21-43d4-b249-450a09d40255",
                  "name": "Jade",
                  "operation": 1,
                  "player_condition": {
                    "type": "skilltree:none"
                  },
                  "player_multiplier": {
                    "type": "skilltree:none"
                  }
                }
              }
            }
          },
          {
            "bonus_provider": {
              "type": "skilltree:simple",
              "item_bonus": {
                "type": "skilltree:skill_bonus",
                "skill_bonus": {
                  "type": "skilltree:attribute",
                  "amount": 0.09999999776482582,
                  "attribute": "minecraft:generic.movement_speed",
                  "id": "80ff4813-e3f1-4d5c-9bd2-e39e8bd31084",
                  "name": "Jade",
                  "operation": 1,
                  "player_condition": {
                    "type": "skilltree:none"
                  },
                  "player_multiplier": {
                    "type": "skilltree:none"
                  }
                }
              }
            }
          },
          {
            "bonus_provider": {
              "type": "skilltree:simple",
              "item_bonus": {
                "type": "skilltree:skill_bonus",
                "skill_bonus": {
                  "type": "skilltree:attribute",
                  "amount": 0.09999999776482582,
                  "attribute": "minecraft:generic.attack_speed",
                  "id": "1903ea1e-1462-426d-b482-150160891497",
                  "name": "Jade",
                  "operation": 1,
                  "player_condition": {
                    "type": "skilltree:none"
                  },
                  "player_multiplier": {
                    "type": "skilltree:none"
                  }
                }
              }
            }
          },
          {
            "bonus_provider": {
              "type": "skilltree:simple",
              "item_bonus": {
                "type": "skilltree:skill_bonus",
                "skill_bonus": {
                  "type": "skilltree:gained_experience",
                  "experience_source": "mobs",
                  "multiplier": 0.25
                }
              }
            }
          },
          {
            "bonus_provider": {
              "type": "skilltree:simple",
              "item_bonus": {
                "type": "skilltree:skill_bonus",
                "skill_bonus": {
                  "type": "skilltree:attribute",
                  "amount": 0.09999999776482582,
                  "attribute": "skilltree:blocking",
                  "id": "746f1e01-9e2b-4840-b4aa-bd68314da979",
                  "name": "Jade",
                  "operation": 1,
                  "player_condition": {
                    "type": "skilltree:none"
                  },
                  "player_multiplier": {
                    "type": "skilltree:none"
                  }
                }
              }
            }
          },
          {
            "bonus_provider": {
              "type": "skilltree:simple",
              "item_bonus": {
                "type": "skilltree:skill_bonus",
                "skill_bonus": {
                  "type": "skilltree:attribute",
                  "amount": 0.04999999888241291,
                  "attribute": "skilltree:evasion",
                  "id": "a085598b-5cf3-47fb-a9f6-7d22f19a5c56",
                  "name": "Jade",
                  "operation": 1,
                  "player_condition": {
                    "type": "skilltree:none"
                  },
                  "player_multiplier": {
                    "type": "skilltree:none"
                  }
                }
              }
            }
          },
          {
            "bonus_provider": {
              "type": "skilltree:simple",
              "item_bonus": {
                "type": "skilltree:skill_bonus",
                "skill_bonus": {
                  "type": "skilltree:attribute",
                  "amount": 1.0000000149011612,
                  "attribute": "minecraft:generic.luck",
                  "id": "d2bc7836-37d0-4a03-ae56-35617c622374",
                  "name": "Citrine",
                  "operation": 0,
                  "player_condition": {
                    "type": "skilltree:none"
                  },
                  "player_multiplier": {
                    "type": "skilltree:none"
                  }
                }
              }
            }
          },
          {
            "bonus_provider": {
              "type": "skilltree:simple",
              "item_bonus": {
                "type": "skilltree:skill_bonus",
                "skill_bonus": {
                  "type": "skilltree:jump_height",
                  "multiplier": 0.099999994,
                  "player_condition": {
                    "type": "skilltree:none"
                  }
                }
              }
            }
          },
          {
            "bonus_provider": {
              "type": "skilltree:simple",
              "item_bonus": {
                "type": "skilltree:skill_bonus",
                "skill_bonus": {
                  "type": "skilltree:crit_chance",
                  "chance": 0.099999994,
                  "damage_condition": {
                    "type": "skilltree:none"
                  },
                  "player_condition": {
                    "type": "skilltree:none"
                  },
                  "player_multiplier": {
                    "type": "skilltree:none"
                  },
                  "target_condition": {
                    "type": "skilltree:none"
                  }
                }
              }
            }
          },
          {
            "bonus_provider": {
              "type": "skilltree:simple",
              "item_bonus": {
                "type": "skilltree:skill_bonus",
                "skill_bonus": {
                  "type": "skilltree:loot_duplication",
                  "chance": 0.099999994,
                  "loot_type": "gems",
                  "multiplier": 2.0
                }
              }
            }
          },
          {
            "bonus_provider": {
              "type": "skilltree:simple",
              "item_bonus": {
                "type": "skilltree:skill_bonus",
                "skill_bonus": {
                  "type": "skilltree:attribute",
                  "amount": 0.09999999776482582,
                  "attribute": "minecraft:generic.luck",
                  "id": "e3869b91-8330-4928-aaa7-2b181dcafa65",
                  "name": "Citrine",
                  "operation": 1,
                  "player_condition": {
                    "type": "skilltree:none"
                  },
                  "player_multiplier": {
                    "type": "skilltree:none"
                  }
                }
              }
            }
          },
          {
            "bonus_provider": {
              "type": "skilltree:simple",
              "item_bonus": {
                "type": "skilltree:skill_bonus",
                "skill_bonus": {
                  "type": "skilltree:loot_duplication",
                  "chance": 0.099999994,
                  "loot_type": "fishing",
                  "multiplier": 1.0
                }
              }
            }
          },
          {
            "bonus_provider": {
              "type": "skilltree:simple",
              "item_bonus": {
                "type": "skilltree:skill_bonus",
                "skill_bonus": {
                  "type": "skilltree:incoming_healing",
                  "multiplier": 0.099999994,
                  "player_condition": {
                    "type": "skilltree:none"
                  },
                  "player_multiplier": {
                    "type": "skilltree:none"
                  }
                }
              }
            }
          },
          {
            "bonus_provider": {
              "type": "skilltree:simple",
              "item_bonus": {
                "type": "skilltree:skill_bonus",
                "skill_bonus": {
                  "type": "skilltree:attribute",
                  "amount": 0.09999999776482582,
                  "attribute": "skilltree:regeneration",
                  "id": "839353c8-008b-4474-91ce-b11207589e14",
                  "name": "Ruby",
                  "operation": 0,
                  "player_condition": {
                    "type": "skilltree:none"
                  },
                  "player_multiplier": {
                    "type": "skilltree:none"
                  }
                }
              }
            }
          },
          {
            "bonus_provider": {
              "type": "skilltree:simple",
              "item_bonus": {
                "type": "skilltree:skill_bonus",
                "skill_bonus": {
                  "type": "skilltree:attribute",
                  "amount": 0.5000000074505806,
                  "attribute": "skilltree:life_per_hit",
                  "id": "0a88b25d-fdba-4210-aca8-ed59f583c87e",
                  "name": "Ruby",
                  "operation": 0,
                  "player_condition": {
                    "type": "skilltree:none"
                  },
                  "player_multiplier": {
                    "type": "skilltree:none"
                  }
                }
              }
            }
          },
          {
            "bonus_provider": {
              "type": "skilltree:simple",
              "item_bonus": {
                "type": "skilltree:skill_bonus",
                "skill_bonus": {
                  "type": "skilltree:attribute",
                  "amount": 0.09999999776482582,
                  "attribute": "minecraft:generic.max_health",
                  "id": "82fd1b9d-a55c-4537-83ef-3a85783c9bdf",
                  "name": "Ruby",
                  "operation": 1,
                  "player_condition": {
                    "type": "skilltree:none"
                  },
                  "player_multiplier": {
                    "type": "skilltree:none"
                  }
                }
              }
            }
          },
          {
            "bonus_provider": {
              "type": "skilltree:simple",
              "item_bonus": {
                "type": "skilltree:skill_bonus",
                "skill_bonus": {
                  "type": "skilltree:attribute",
                  "amount": 0.5000000074505806,
                  "attribute": "skilltree:life_on_block",
                  "id": "3b5a46b3-7315-4984-90d1-1b832cb32a20",
                  "name": "Ruby",
                  "operation": 0,
                  "player_condition": {
                    "type": "skilltree:none"
                  },
                  "player_multiplier": {
                    "type": "skilltree:none"
                  }
                }
              }
            }
          },
          {
            "bonus_provider": {
              "type": "skilltree:simple",
              "item_bonus": {
                "type": "skilltree:skill_bonus",
                "skill_bonus": {
                  "type": "skilltree:incoming_healing",
                  "multiplier": 0.049999997,
                  "player_condition": {
                    "type": "skilltree:none"
                  },
                  "player_multiplier": {
                    "type": "skilltree:none"
                  }
                }
              }
            }
          },
          {
            "bonus_provider": {
              "type": "skilltree:simple",
              "item_bonus": {
                "type": "skilltree:skill_bonus",
                "skill_bonus": {
                  "type": "skilltree:attribute",
                  "amount": 1.0000000149011612,
                  "attribute": "minecraft:generic.armor_toughness",
                  "id": "88e3ffc6-1a30-431d-8f89-5696aae11988",
                  "name": "Sapphire",
                  "operation": 0,
                  "player_condition": {
                    "type": "skilltree:none"
                  },
                  "player_multiplier": {
                    "type": "skilltree:none"
                  }
                }
              }
            }
          },
          {
            "bonus_provider": {
              "type": "skilltree:simple",
              "item_bonus": {
                "type": "skilltree:skill_bonus",
                "skill_bonus": {
                  "type": "skilltree:attribute",
                  "amount": 0.09999999776482582,
                  "attribute": "minecraft:generic.knockback_resistance",
                  "id": "14ee575c-2fa9-4303-a0c9-76ac03b282df",
                  "name": "Sapphire",
                  "operation": 0,
                  "player_condition": {
                    "type": "skilltree:none"
                  },
                  "player_multiplier": {
                    "type": "skilltree:none"
                  }
                }
              }
            }
          },
          {
            "bonus_provider": {
              "type": "skilltree:simple",
              "item_bonus": {
                "type": "skilltree:skill_bonus",
                "skill_bonus": {
                  "type": "skilltree:damage",
                  "chance": 0.099999994,
                  "damage_condition": {
                    "type": "skilltree:none"
                  },
                  "operation": 1,
                  "player_condition": {
                    "type": "skilltree:none"
                  },
                  "player_multiplier": {
                    "type": "skilltree:none"
                  },
                  "target_condition": {
                    "type": "skilltree:none"
                  }
                }
              }
            }
          },
          {
            "bonus_provider": {
              "type": "skilltree:simple",
              "item_bonus": {
                "type": "skilltree:skill_bonus",
                "skill_bonus": {
                  "type": "skilltree:attribute",
                  "amount": 0.09999999776482582,
                  "attribute": "minecraft:generic.armor",
                  "id": "3c39f103-1097-4034-b315-e04e328cba46",
                  "name": "Sapphire",
                  "operation": 1,
                  "player_condition": {
                    "type": "skilltree:none"
                  },
                  "player_multiplier": {
                    "type": "skilltree:none"
                  }
                }
              }
            }
          },
          {
            "bonus_provider": {
              "type": "skilltree:simple",
              "item_bonus": {
                "type": "skilltree:durability",
                "chance": 100.0,
                "operation": 0
              }
            }
          },
          {
            "bonus_provider": {
              "type": "skilltree:simple",
              "item_bonus": {
                "type": "skilltree:skill_bonus",
                "skill_bonus": {
                  "type": "skilltree:attribute",
                  "amount": 0.04999999888241291,
                  "attribute": "skilltree:blocking",
                  "id": "f63561c0-bd68-4e22-be8e-26aa1533cd1f",
                  "name": "Sapphire",
                  "operation": 1,
                  "player_condition": {
                    "type": "skilltree:none"
                  },
                  "player_multiplier": {
                    "type": "skilltree:none"
                  }
                }
              }
            }
          }
        ]
      },
      "item_condition": {
        "type": "skilltree:none"
      }
    }
  ],
  "id": "skilltree:iriscite_5"
}