{
  "bonuses": [
    {
      "bonus_provider": {
        "type": "skilltree:simple",
        "item_bonus": {
          "type": "skilltree:skill_bonus",
          "skill_bonus": {
            "type": "skilltree:attribute",
            "amount": 0.03999999910593033,
            "attribute": "skilltree:evasion",
            "id": "e30a89e2-cf8a-4bdb-856d-a7916c7dc426",
            "name": "Jade",
            "operation": 1,
            "player_condition": {
              "type": "skilltree:none"
            },
            "player_multiplier": {
              "type": "skilltree:none"
            }
          }
        }
      },
      "item_condition": {
        "type": "skilltree:armor",
        "armor_type": "chestplate"
      }
    },
    {
      "bonus_provider": {
        "type": "skilltree:simple",
        "item_bonus": {
          "type": "skilltree:skill_bonus",
          "skill_bonus": {
            "type": "skilltree:attribute",
            "amount": 0.03999999910593033,
            "attribute": "minecraft:generic.movement_speed",
            "id": "7ee3b2e7-62fc-43eb-98b1-1c8c35e44efe",
            "name": "Jade",
            "operation": 1,
            "player_condition": {
              "type": "skilltree:none"
            },
            "player_multiplier": {
              "type": "skilltree:none"
            }
          }
        }
      },
      "item_condition": {
        "type": "skilltree:armor",
        "armor_type": "boots"
      }
    },
    {
      "bonus_provider": {
        "type": "skilltree:simple",
        "item_bonus": {
          "type": "skilltree:skill_bonus",
          "skill_bonus": {
            "type": "skilltree:attribute",
            "amount": 0.03999999910593033,
            "attribute": "minecraft:generic.attack_speed",
            "id": "b87d4a4f-d156-44e1-a135-871a4bc3318a",
            "name": "Jade",
            "operation": 1,
            "player_condition": {
              "type": "skilltree:none"
            },
            "player_multiplier": {
              "type": "skilltree:none"
            }
          }
        }
      },
      "item_condition": {
        "type": "skilltree:weapon",
        "weapon_type": "any"
      }
    },
    {
      "bonus_provider": {
        "type": "skilltree:simple",
        "item_bonus": {
          "type": "skilltree:skill_bonus",
          "skill_bonus": {
            "type": "skilltree:gained_experience",
            "experience_source": "mobs",
            "multiplier": 0.1
          }
        }
      },
      "item_condition": {
        "type": "skilltree:armor",
        "armor_type": "helmet"
      }
    },
    {
      "bonus_provider": {
        "type": "skilltree:simple",
        "item_bonus": {
          "type": "skilltree:skill_bonus",
          "skill_bonus": {
            "type": "skilltree:attribute",
            "amount": 0.03999999910593033,
            "attribute": "skilltree:blocking",
            "id": "5684d79f-2ed3-4197-af07-e75a98437416",
            "name": "Jade",
            "operation": 1,
            "player_condition": {
              "type": "skilltree:none"
            },
            "player_multiplier": {
              "type": "skilltree:none"
            }
          }
        }
      },
      "item_condition": {
        "type": "skilltree:armor",
        "armor_type": "shield"
      }
    },
    {
      "bonus_provider": {
        "type": "skilltree:simple",
        "item_bonus": {
          "type": "skilltree:skill_bonus",
          "skill_bonus": {
            "type": "skilltree:attribute",
            "amount": 0.019999999552965164,
            "attribute": "skilltree:evasion",
            "id": "83a6d5ad-c74a-4d8a-85e0-5285221948d4",
            "name": "Jade",
            "operation": 1,
            "player_condition": {
              "type": "skilltree:none"
            },
            "player_multiplier": {
              "type": "skilltree:none"
            }
          }
        }
      },
      "item_condition": {
        "type": "skilltree:jewelry"
      }
    }
  ],
  "id": "skilltree:jade_3"
}